hy_sqlite.py
hy_sqlite-0.0.1.dist-info/LICENSE
hy_sqlite-0.0.1.dist-info/METADATA
hy_sqlite-0.0.1.dist-info/WHEEL
hy_sqlite-0.0.1.dist-info/top_level.txt
hy_sqlite-0.0.1.dist-info/RECORD
