Metadata-Version: 2.1
Name: hy_sqlite
Version: 0.0.1
Summary: Module de requettes sqlite sans sql
Author: Hypo
Classifier: Programming Language :: Python :: 3
Classifier: License :: OSI Approved :: MIT License
Classifier: Operating System :: OS Independent
Requires-Python: >3.6
License-File: LICENSE
